{
  "name": "Just Legal Solutions",
  "category": "Process Server",
  "phone": "(539) 367-6832",
  "website": "https://justlegalsolutions.org",
  "address": {
    "street": "564 E 138th Pl",
    "city": "Glenpool",
    "state": "OK",
    "zip": "74033"
  },
  "description": "Just Legal Solutions provides certified process serving, legal document delivery, same-day and rush service, executive business support, court filings, courier deliveries, HR/payroll, and more throughout Tulsa County, Broken Arrow, Sapulpa, Glenpool, Bixby, and all surrounding areas. Licensed, bonded, and locally trusted. Emergency and 24/7 process server available.",
  "services": [
    "Process Serving",
    "Legal Document Delivery",
    "Court Filing Services",
    "Same-Day Service",
    "Rush Service",
    "Subpoena Service",
    "Eviction Service",
    "Business Courier Services",
    "Payroll Support",
    "Executive Assistant",
    "HR/Staffing Assistance",
    "Emergency Service"
  ],
  "attributes": [
    "Licensed",
    "Bonded",
    "Insured",
    "Same-day service",
    "Weekend availability",
    "Emergency service",
    "Free consultation",
    "24/7 availability",
    "Locally owned",
    "Tulsa County specialist"
  ],
  "hours": {
    "monday": "00:00-23:59",
    "tuesday": "00:00-23:59",
    "wednesday": "00:00-23:59",
    "thursday": "00:00-23:59",
    "friday": "00:00-23:59",
    "saturday": "00:00-23:59",
    "sunday": "00:00-23:59"
  },
  "competitorAnalysis": {
    "yourserved.com": {
      "weaknesses": [
        "Generic service",
        "Higher pricing",
        "Slower response"
      ],
      "ourAdvantages": [
        "Local focus",
        "Certified professionals",
        "Same-day emergency service",
        "Personal customer support"
      ]
    }
  }
}
